csdmpy/__init__.py
csdmpy/__main__.py
csdmpy/abstract_list.py
csdmpy/csdm.py
csdmpy/helper_functions.py
csdmpy/statistics.py
csdmpy/tests.py
csdmpy/units.py
csdmpy/utils.py
csdmpy/dependent_variable/__init__.py
csdmpy/dependent_variable/base_class.py
csdmpy/dependent_variable/decoder.py
csdmpy/dependent_variable/download.py
csdmpy/dependent_variable/external.py
csdmpy/dependent_variable/internal.py
csdmpy/dependent_variable/sparse.py
csdmpy/dimension/__init__.py
csdmpy/dimension/base.py
csdmpy/dimension/labeled.py
csdmpy/dimension/linear.py
csdmpy/dimension/monotonic.py
csdmpy/dimension/quantitative.py
csdmpy/numpy_wrapper/__init__.py
csdmpy/numpy_wrapper/apodize.py
csdmpy-0.7.0.dist-info/LICENSE
csdmpy-0.7.0.dist-info/METADATA
csdmpy-0.7.0.dist-info/WHEEL
csdmpy-0.7.0.dist-info/top_level.txt
csdmpy-0.7.0.dist-info/RECORD
