Metadata-Version: 2.1
Name: csdmpy
Version: 0.7.0
Summary: A python module for the core scientific dataset model.
Home-page: https://github.com/DeepanshS/csdmpy/
Author: Deepansh Srivastava
Author-email: srivastava.89@osu.edu
License: BSD-3-Clause
Classifier: Intended Audience :: Science/Research
Classifier: Intended Audience :: Developers
Classifier: Operating System :: OS Independent
Classifier: Development Status :: 4 - Beta
Classifier: License :: OSI Approved :: BSD License
Classifier: Programming Language :: Python
Classifier: Programming Language :: Python :: 3
Classifier: Programming Language :: Python :: 3.9
Classifier: Programming Language :: Python :: 3.10
Classifier: Programming Language :: Python :: 3.11
Classifier: Programming Language :: Python :: 3.12
Classifier: Programming Language :: Python :: 3.13
Classifier: Topic :: Scientific/Engineering
Requires-Python: >=3.9
License-File: LICENSE
Requires-Dist: numpy >=1.20
Requires-Dist: setuptools >=27.3
Requires-Dist: requests >=2.21.0
Requires-Dist: numexpr >=2.7.0
Provides-Extra: matplotlib
Requires-Dist: matplotlib >=3.0 ; extra == 'matplotlib'
